backports/__init__.py
backports/html/__init__.py
backports/html/entities.py
backports/html/parser.py
backports.html-1.1.0.dist-info/METADATA
backports.html-1.1.0.dist-info/RECORD
backports.html-1.1.0.dist-info/WHEEL
backports.html-1.1.0.dist-info/top_level.txt
