Metadata-Version: 2.1
Name: backports.html
Version: 1.1.0
Summary: Backport of Python 3.4+'s html module
Home-page: https://github.com/frostming/backports.html
Author: Frost Ming
Author-email: mianghong@gmail.com
License: UNKNOWN
Platform: UNKNOWN
Classifier: Development Status :: 5 - Production/Stable
Classifier: Intended Audience :: Developers
Classifier: Programming Language :: Python :: 2.7
Classifier: Programming Language :: Python :: 3
